moseqprep/__init__.py
moseqprep/filter_and_plot_syllables.py
moseqprep/get_duration.py
moseqprep/plot_syl.py
moseqpreprocess-0.1.2.dist-info/LICENSE.txt
moseqpreprocess-0.1.2.dist-info/METADATA
moseqpreprocess-0.1.2.dist-info/WHEEL
moseqpreprocess-0.1.2.dist-info/top_level.txt
moseqpreprocess-0.1.2.dist-info/RECORD
