Metadata-Version: 2.1
Name: moseqpreprocess
Version: 0.1.2
Summary: A package to filter and plot syllables
Home-page: https://github.com/iurillilab/moseqpreprocess
Author: Thomas Wyndham Bush
Author-email: thomaswyndham.bush@unitn.it
Classifier: Programming Language :: Python :: 3
Classifier: License :: OSI Approved :: MIT License
Classifier: Operating System :: OS Independent
Requires-Python: >=3.6
License-File: LICENSE.txt
Requires-Dist: numpy
Requires-Dist: pandas
Requires-Dist: matplotlib
